create_litestar/__init__.py
create_litestar/__main__.py
create_litestar/__metadata__.py
create_litestar/py.typed
create_litestar/commands/logging.py
create_litestar/commands/object_type.py
create_litestar/commands/openapi.py
create_litestar/commands/orm.py
create_litestar/commands/plugins.py
create_litestar/commands/template.py
create_litestar/commands/web_server.py
create_litestar/helpers/cli.py
create_litestar/helpers/constants.py
create_litestar/helpers/project.py
create_litestar/helpers/validators.py
create_litestar/model/project.py
create_litestar/templates/basic/.env.example
create_litestar/templates/basic/README.md.jinja
create_litestar/templates/basic/pyproject.toml.jinja
create_litestar/templates/basic/app/__init__.py
create_litestar/templates/basic/app/__main__.py
create_litestar/templates/basic/app/__metadata__.py.jinja
create_litestar/templates/basic/app/asgi.py.jinja
create_litestar/templates/basic/app/py.typed
create_litestar/templates/basic/app/config/compression.py.jinja
create_litestar/templates/basic/app/config/constants.py.jinja
create_litestar/templates/basic/app/config/routes.py
create_litestar/templates/basic/app/config/settings.py.jinja
create_litestar/templates/basic/app/config/{% if use_cors_csrf %}cors.py{% endif %}.jinja
create_litestar/templates/basic/app/config/{% if use_logging %}log.py{% endif %}.jinja
create_litestar/templates/basic/app/config/{% if use_openapi %}openapi.py{% endif %}.jinja
create_litestar/templates/basic/app/config/{% if use_web_server and web_server == 'granian' %}web_server.py{% endif %}.jinja
create_litestar/templates/basic/app/db/migrations/__init__.py
create_litestar/templates/basic/app/db/migrations/alembic.ini
create_litestar/templates/basic/app/db/migrations/env.py
create_litestar/templates/basic/app/db/migrations/script.py.mako
create_litestar/templates/basic/app/domain/system/__init__.py
create_litestar/templates/basic/app/domain/system/controllers.py
create_litestar-0.1.2.dist-info/METADATA
create_litestar-0.1.2.dist-info/WHEEL
create_litestar-0.1.2.dist-info/entry_points.txt
create_litestar-0.1.2.dist-info/licenses/LICENSE
create_litestar-0.1.2.dist-info/RECORD
